{
  "common": {
    "name": "homewizard",
    "version": "0.6.7",
    "news": {
      "0.6.7": {
        "en": "Documentation: rewrote release notes in user-friendly style across all languages.",
        "de": "Dokumentation: Release-Notes in alle Sprachen User-orientiert neu geschrieben.",
        "ru": "Документация: примечания к релизу переписаны в дружественном к пользователю стиле на всех языках.",
        "pt": "Documentação: notas de release reescritas em estilo amigável ao usuário em todos os idiomas.",
        "nl": "Documentatie: release-notes herschreven in gebruikersvriendelijke stijl in alle talen.",
        "fr": "Documentation : notes de version réécrites dans un style adapté à l'utilisateur dans toutes les langues.",
        "it": "Documentazione: note di release riscritte in stile user-friendly in tutte le lingue.",
        "es": "Documentación: notas de versión reescritas en estilo amigable para el usuario en todos los idiomas.",
        "pl": "Dokumentacja: notatki wydania przepisane w przyjaznym dla użytkownika stylu we wszystkich językach.",
        "uk": "Документація: нотатки до релізу переписано у дружньому до користувача стилі усіма мовами.",
        "zh-cn": "文档：所有语言的发布说明已重写为用户友好的风格。"
      },
      "0.6.6": {
        "en": "Internal cleanup. No user-facing changes.",
        "de": "Interne Bereinigung. Keine User-sichtbaren Änderungen.",
        "ru": "Внутренняя очистка. Без видимых изменений для пользователя.",
        "pt": "Limpeza interna. Sem alterações visíveis para o usuário.",
        "nl": "Interne opschoning. Geen wijzigingen voor de gebruiker.",
        "fr": "Nettoyage interne. Aucune modification visible pour l'utilisateur.",
        "it": "Pulizia interna. Nessuna modifica visibile all'utente.",
        "es": "Limpieza interna. Sin cambios visibles para el usuario.",
        "pl": "Wewnętrzne porządki. Brak zmian widocznych dla użytkownika.",
        "uk": "Внутрішнє прибирання. Без помітних для користувача змін.",
        "zh-cn": "内部清理。对用户无可见变化。"
      },
      "0.6.5": {
        "en": "Crash defense: process-level error handlers. Min js-controller restored to >=6.0.11.",
        "de": "Crash-Schutz: process-level Error-Handler. Min js-controller zurück auf >=6.0.11.",
        "ru": "Защита от сбоев: process-level обработчики ошибок. Мин. js-controller восстановлен на >=6.0.11.",
        "pt": "Proteção contra falhas: handlers de erro process-level. Mín. js-controller restaurado para >=6.0.11.",
        "nl": "Crashbescherming: process-level error-handlers. Min. js-controller hersteld op >=6.0.11.",
        "fr": "Défense contre les crashs : handlers d'erreur process-level. Min js-controller rétabli à >=6.0.11.",
        "it": "Difesa anti-crash: handler di errore process-level. Min js-controller ripristinato a >=6.0.11.",
        "es": "Defensa contra fallos: handlers de error process-level. Mín. js-controller restaurado a >=6.0.11.",
        "pl": "Ochrona przed crashem: handlery błędów process-level. Min. js-controller przywrócony do >=6.0.11.",
        "uk": "Захист від збоїв: process-level обробники помилок. Мін. js-controller повернено на >=6.0.11.",
        "zh-cn": "崩溃防护：process-level 错误处理器。最低 js-controller 恢复为 >=6.0.11。"
      },
      "0.6.4": {
        "en": "Internal hardening. No user-facing changes.",
        "de": "Interne Härtung. Keine User-sichtbaren Änderungen.",
        "ru": "Внутреннее усиление. Без видимых изменений для пользователя.",
        "pt": "Endurecimento interno. Sem alterações visíveis para o usuário.",
        "nl": "Interne verharding. Geen wijzigingen voor de gebruiker.",
        "fr": "Durcissement interne. Aucune modification visible pour l'utilisateur.",
        "it": "Hardening interno. Nessuna modifica visibile all'utente.",
        "es": "Endurecimiento interno. Sin cambios visibles para el usuario.",
        "pl": "Wewnętrzne wzmocnienie. Brak zmian widocznych dla użytkownika.",
        "uk": "Внутрішнє зміцнення. Без помітних для користувача змін.",
        "zh-cn": "内部加固。对用户无可见变化。"
      },
      "0.6.3": {
        "en": "WebSocket and REST input hardening. Stops endless reconnect when the device token is invalid.",
        "de": "WebSocket- und REST-Input-Härtung. Beendet Endlos-Reconnect bei ungültigem Geräte-Token.",
        "ru": "Усиление input WebSocket и REST. Прекращает бесконечный reconnect при недействительном токене устройства.",
        "pt": "Endurecimento de entrada WebSocket e REST. Para a reconexão infinita quando o token do dispositivo é inválido.",
        "nl": "WebSocket- en REST-input-verharding. Stopt eindeloze reconnect bij ongeldig apparaat-token.",
        "fr": "Durcissement des entrées WebSocket et REST. Arrête la reconnexion infinie en cas de token d'appareil invalide.",
        "it": "Hardening input WebSocket e REST. Ferma riconnessione infinita su token dispositivo non valido.",
        "es": "Endurecimiento de entrada WebSocket y REST. Detiene la reconexión infinita con token de dispositivo inválido.",
        "pl": "Wzmocnienie input WebSocket i REST. Zatrzymuje nieskończony reconnect przy nieprawidłowym tokenie urządzenia.",
        "uk": "Зміцнення input WebSocket та REST. Припиняє нескінченний reconnect при недійсному токені пристрою.",
        "zh-cn": "WebSocket 和 REST 输入加固。设备 token 无效时停止无限重连。"
      },
      "0.6.2": {
        "en": "Fix: hanging promise on response stream errors. Safer adapter shutdown.",
        "de": "Fix: hängender Promise bei Response-Stream-Fehlern. Sichereres Adapter-Shutdown.",
        "ru": "Fix: зависший promise при ошибках response-stream. Более безопасное завершение работы адаптера.",
        "pt": "Fix: promise pendurada em erros de response stream. Encerramento mais seguro do adaptador.",
        "nl": "Fix: hangende promise bij response-stream-fouten. Veiliger afsluiten van de adapter.",
        "fr": "Fix : promesse bloquée sur erreurs de response stream. Arrêt plus sûr de l'adaptateur.",
        "it": "Fix: promise sospesa su errori response stream. Spegnimento più sicuro dell'adattatore.",
        "es": "Fix: promise colgada en errores de response stream. Apagado más seguro del adaptador.",
        "pl": "Fix: zawieszony promise przy błędach response stream. Bezpieczniejsze zamykanie adaptera.",
        "uk": "Fix: завислий promise при помилках response-stream. Безпечніше завершення роботи адаптера.",
        "zh-cn": "修复：response stream 错误时的挂起 promise。更安全的适配器关闭。"
      },
      "0.6.1": {
        "en": "Internal cleanup. No user-facing changes.",
        "de": "Interne Bereinigung. Keine User-sichtbaren Änderungen.",
        "ru": "Внутренняя очистка. Без видимых изменений для пользователя.",
        "pt": "Limpeza interna. Sem alterações visíveis para o usuário.",
        "nl": "Interne opschoning. Geen wijzigingen voor de gebruiker.",
        "fr": "Nettoyage interne. Aucune modification visible pour l'utilisateur.",
        "it": "Pulizia interna. Nessuna modifica visibile all'utente.",
        "es": "Limpieza interna. Sin cambios visibles para el usuario.",
        "pl": "Wewnętrzne porządki. Brak zmian widocznych dla użytkownika.",
        "uk": "Внутрішнє прибирання. Без помітних для користувача змін.",
        "zh-cn": "内部清理。对用户无可见变化。"
      }
    },
    "titleLang": {
      "en": "HomeWizard Energy",
      "de": "HomeWizard Energy",
      "ru": "HomeWizard Energy",
      "pt": "HomeWizard Energy",
      "nl": "HomeWizard Energy",
      "fr": "HomeWizard Energy",
      "it": "HomeWizard Energy",
      "es": "HomeWizard Energy",
      "pl": "HomeWizard Energy",
      "uk": "HomeWizard Energy",
      "zh-cn": "HomeWizard Energy"
    },
    "desc": {
      "en": "Real-time energy monitoring from HomeWizard devices (P1 Meter, kWh Meter, Battery) via API v2 with WebSocket push",
      "de": "Echtzeit-Energieüberwachung von HomeWizard-Geräten (P1 Meter, kWh Meter, Batterie) via API v2 mit WebSocket-Push",
      "ru": "Мониторинг энергии в реальном времени от устройств HomeWizard (P1 Meter, kWh Meter, Battery) через API v2 с WebSocket push",
      "pt": "Monitoramento de energia em tempo real de dispositivos HomeWizard (P1 Meter, kWh Meter, Battery) via API v2 com WebSocket push",
      "nl": "Realtime energiemonitoring van HomeWizard-apparaten (P1 Meter, kWh Meter, Battery) via API v2 met WebSocket push",
      "fr": "Surveillance énergétique en temps réel des appareils HomeWizard (P1 Meter, kWh Meter, Battery) via API v2 avec WebSocket push",
      "it": "Monitoraggio energetico in tempo reale da dispositivi HomeWizard (P1 Meter, kWh Meter, Battery) via API v2 con WebSocket push",
      "es": "Monitoreo de energía en tiempo real de dispositivos HomeWizard (P1 Meter, kWh Meter, Battery) vía API v2 con WebSocket push",
      "pl": "Monitorowanie energii w czasie rzeczywistym z urządzeń HomeWizard (P1 Meter, kWh Meter, Battery) przez API v2 z WebSocket push",
      "uk": "Моніторинг енергії в реальному часі від пристроїв HomeWizard (P1 Meter, kWh Meter, Battery) через API v2 з WebSocket push",
      "zh-cn": "通过 API v2 和 WebSocket 推送实时监控 HomeWizard 设备（P1 Meter、kWh Meter、Battery）的能源数据"
    },
    "authors": [
      "krobi <krobi@power-dreams.com>"
    ],
    "keywords": [
      "homewizard",
      "energy",
      "p1",
      "meter",
      "smartmeter",
      "websocket",
      "power"
    ],
    "licenseInformation": {
      "license": "MIT",
      "type": "free"
    },
    "platform": "Javascript/Node.js",
    "icon": "homewizard.svg",
    "extIcon": "https://raw.githubusercontent.com/krobipd/ioBroker.homewizard/main/admin/homewizard.svg",
    "readme": "https://github.com/krobipd/ioBroker.homewizard/blob/main/README.md",
    "enabled": true,
    "tier": 3,
    "loglevel": "info",
    "mode": "daemon",
    "type": "energy",
    "compact": true,
    "connectionType": "local",
    "dataSource": "push",
    "adminUI": {
      "config": "json"
    },
    "supportedMessages": {
      "stopInstance": true
    },
    "dependencies": [
      {
        "js-controller": ">=7.0.7"
      }
    ],
    "globalDependencies": [
      {
        "admin": ">=7.7.22"
      }
    ]
  },
  "encryptedNative": [],
  "protectedNative": [],
  "native": {},
  "instanceObjects": [
    {
      "_id": "info",
      "type": "channel",
      "common": {
        "name": "Adapter Information"
      },
      "native": {}
    },
    {
      "_id": "info.connection",
      "type": "state",
      "common": {
        "name": "Connection status",
        "type": "boolean",
        "role": "indicator.connected",
        "read": true,
        "write": false,
        "def": false
      },
      "native": {}
    },
    {
      "_id": "startPairing",
      "type": "state",
      "common": {
        "name": "Start pairing mode",
        "type": "boolean",
        "role": "button",
        "read": false,
        "write": true,
        "def": false
      },
      "native": {}
    },
    {
      "_id": "pairingIp",
      "type": "state",
      "common": {
        "name": {
          "en": "Device IP for manual pairing",
          "de": "Geräte-IP für manuelles Pairing",
          "ru": "IP-адрес устройства для ручного сопряжения",
          "pt": "IP do dispositivo para emparelhamento manual",
          "nl": "Apparaat-IP voor handmatig koppelen",
          "fr": "IP de l'appareil pour l'appairage manuel",
          "it": "IP del dispositivo per l'accoppiamento manuale",
          "es": "IP del dispositivo para emparejamiento manual",
          "pl": "IP urządzenia do ręcznego parowania",
          "uk": "IP пристрою для ручного сполучення",
          "zh-cn": "用于手动配对的设备 IP"
        },
        "type": "string",
        "role": "text",
        "read": true,
        "write": true,
        "def": ""
      },
      "native": {}
    }
  ]
}
